psat/__init__.py
psat/psat.py
psat_result_api-1.0.3.dist-info/METADATA
psat_result_api-1.0.3.dist-info/WHEEL
psat_result_api-1.0.3.dist-info/top_level.txt
psat_result_api-1.0.3.dist-info/RECORD
