Metadata-Version: 2.1
Name: psat-result-api
Version: 1.0.3
Summary: Python module to interact with the Proofpoint Security Awareness Training (PSAT) Results API
Home-page: https://github.com/regg00/psat-result-api
Author: Régis Tremblay Lefrançois
Author-email: regg00@gmail.com
License: UNKNOWN
Project-URL: Bug Tracker, https://github.com/regg00/psat-result-api/issues
Platform: UNKNOWN
Classifier: Programming Language :: Python :: 3
Classifier: License :: OSI Approved :: MIT License
Classifier: Operating System :: OS Independent
Requires-Python: >=3.6
